passgenpro/__init__.py
passgenpro/generator.py
passgenpro-0.1.0.dist-info/METADATA
passgenpro-0.1.0.dist-info/WHEEL
passgenpro-0.1.0.dist-info/top_level.txt
passgenpro-0.1.0.dist-info/RECORD
