Metadata-Version: 2.4
Name: passgenpro
Version: 0.1.0
Summary: Simple yet powerful password generator library.
Author: Eldar Eliyev
Author-email: eldar@example.com
Requires-Python: >=3.7
Dynamic: author
Dynamic: author-email
Dynamic: description
Dynamic: description-content-type
Dynamic: requires-python
Dynamic: summary
